rocelib/__init__.py
rocelib/datasets/DatasetLoader.py
rocelib/datasets/ExampleDatasets.py
rocelib/datasets/__init__.py
rocelib/datasets/custom_datasets/CsvDatasetLoader.py
rocelib/datasets/provided_datasets/AdultDatasetLoader.py
rocelib/datasets/provided_datasets/ExampleDatasetLoader.py
rocelib/datasets/provided_datasets/IonosphereDatasetLoader.py
rocelib/datasets/provided_datasets/IrisDatasetLoader.py
rocelib/datasets/provided_datasets/TitanicDatasetLoader.py
rocelib/datasets/provided_datasets/__init__.py
rocelib/enums/__init__.py
rocelib/enums/dataset_enums.py
rocelib/enums/model_enums.py
rocelib/evaluations/DistanceEvaluator.py
rocelib/evaluations/ManifoldEvaluator.py
rocelib/evaluations/RecourseEvaluator.py
rocelib/evaluations/RobustnessProportionEvaluator.py
rocelib/evaluations/ValidityEvaluator.py
rocelib/evaluations/__init__.py
rocelib/evaluations/robustness_evaluations/BaseRobustnessEvaluator.py
rocelib/evaluations/robustness_evaluations/Evaluator.py
rocelib/evaluations/robustness_evaluations/InputChangesRobustnessEvaluator.py
rocelib/evaluations/robustness_evaluations/ModelChangesRobustnessEvaluator.py
rocelib/evaluations/robustness_evaluations/ModelMultiplicityRobustnessEvaluator.py
rocelib/evaluations/robustness_evaluations/NoisyExecutionRobustnessEvaluator.py
rocelib/evaluations/robustness_evaluations/__init__.py
rocelib/evaluations/robustness_evaluations/IC_Robustness_Implementations/SetDistanceRobustnessEvaluator.py
rocelib/evaluations/robustness_evaluations/MC_Robustness_Implementations/ApproximateDeltaRobustnessEvaluator.py
rocelib/evaluations/robustness_evaluations/MC_Robustness_Implementations/DeltaRobustnessEvaluator.py
rocelib/evaluations/robustness_evaluations/MC_Robustness_Implementations/VaRRobustnessEvaluator.py
rocelib/evaluations/robustness_evaluations/MM_Robustness_Implementations/MultiplicityValidityRobustnessEvaluator.py
rocelib/evaluations/robustness_evaluations/NE_Robustness_Implementations/InvalidationRateRobustnessEvaluator.py
rocelib-0.2.3.dist-info/LICENSE
rocelib-0.2.3.dist-info/METADATA
rocelib-0.2.3.dist-info/WHEEL
rocelib-0.2.3.dist-info/top_level.txt
rocelib-0.2.3.dist-info/RECORD
