Metadata-Version: 2.2
Name: RoCELib
Version: 0.2.3
Summary: RoCELib is an open-source Python library designed for benchmarking the robustness of counterfactual explanation (CE) methods.
Author-email: Ivan Artiukhov <ivan.artiukhov22@imperial.ac.uk>, Lorenzo Evans <lorenzo.evans22@imperial.ac.uk>, Shlok Shah <shlok.shah22@imperial.ac.uk>, Ayush Patel <ayush.patel22@imperial.ac.uk>, James Stadler <james.stadler22@imperial.ac.uk>, Seth Mack <seth.mack22@imperial.ac.uk>, Junqi Jiang <junqi.jiang20@imperial.ac.uk>, Luca Marzari <luca.marzari@univr.it>, Aaryan Purohit <aaryan.purohit22@imperial.ac.uk>, Francesco Leofante <f.leofante@imperial.ac.uk>
License: MIT License
Project-URL: Homepage, https://github.com/JStadl/RoCELib
Classifier: Programming Language :: Python :: 3
Classifier: License :: OSI Approved :: MIT License
Classifier: Operating System :: OS Independent
Requires-Python: >=3.9
License-File: LICENSE
Requires-Dist: torch==2.4.1
Requires-Dist: notebook
Requires-Dist: scikit-learn
Requires-Dist: pandas
Requires-Dist: scipy
Requires-Dist: tqdm
Requires-Dist: tabulate
Requires-Dist: streamlit
Requires-Dist: matplotlib
Requires-Dist: seaborn
Requires-Dist: clingo>=5.6.2
Requires-Dist: tensorflow==2.16.2
Requires-Dist: keras==3.0.5
Provides-Extra: dev
Requires-Dist: pytest; extra == "dev"
Provides-Extra: gurobi
Requires-Dist: gurobipy==11.0.1; extra == "gurobi"
